[
    {
        "vid": "6:14:1",
        "tokens": "וְאֵ֛לֶּה₋428` `אֲשֶׁר־₋834` `נָחֲל֥וּ₋5157` `בְנֵֽי־₋1121` `יִשְׂרָאֵ֖ל₋3478` `בְּאֶ֣רֶץ₋776` `כְּנָ֑עַן₋3667` `אֲשֶׁ֨ר₋834` `נִֽחֲל֜וּ₋5157` `אוֹתָ֗ם₋853` `אֶלְעָזָ֤ר₋499` `הַכֹּהֵן֙₋3548` `וִיהוֹשֻׁ֣עַ₋3091` `בִּן־₋1121` `נ֔וּן₋5126` `וְרָאשֵׁ֛י₋7218` `אֲב֥וֹת₋1` `הַמַּטּ֖וֹת₋4294` `לִבְנֵ֥י₋1121` `יִשְׂרָאֵֽל׃₋3478"
    },
    {
        "vid": "6:14:2",
        "tokens": "בְּגוֹרַ֖ל₋1486` `נַחֲלָתָ֑ם₋5159` `כַּאֲשֶׁ֨ר₋834` `צִוָּ֤ה₋6680` `יְהוָה֙₋3068` `בְּיַד־₋3027` `מֹשֶׁ֔ה₋4872` `לְתִשְׁעַ֥ת₋8672` `הַמַּטּ֖וֹת₋4294` `וַחֲצִ֥י₋2677` `הַמַּטֶּֽה׃₋4294"
    },
    {
        "vid": "6:14:3",
        "tokens": "כִּֽי־₋3588` `נָתַ֨ן₋5414` `מֹשֶׁ֜ה₋4872` `נַחֲלַ֨ת₋5159` `שְׁנֵ֤י₋8147` `הַמַּטּוֹת֙₋4294` `וַחֲצִ֣י₋2677` `הַמַּטֶּ֔ה₋4294` `מֵעֵ֖בֶר₋5676` `לַיַּרְדֵּ֑ן₋3383` `וְלַ֨לְוִיִּ֔ם₋3881` `לֹֽא־₋3808` `נָתַ֥ן₋5414` `נַחֲלָ֖ה₋5159` `בְּתוֹכָֽם׃₋8432"
    },
    {
        "vid": "6:14:4",
        "tokens": "כִּֽי־₋3588` `הָי֧וּ₋1961` `בְנֵֽי־₋1121` `יוֹסֵ֛ף₋3130` `שְׁנֵ֥י₋8147` `מַטּ֖וֹת₋4294` `מְנַשֶּׁ֣ה₋4519` `וְאֶפְרָ֑יִם₋669` `וְלֹֽא־₋3808` `נָתְנוּ֩₋5414` `חֵ֨לֶק₋2506` `לַלְוִיִּ֜ם₋3881` `בָּאָ֗רֶץ₋776` `כִּ֤י₋3588` `אִם־₋518` `עָרִים֙₋5892` `לָשֶׁ֔בֶת₋3427` `וּמִ֨גְרְשֵׁיהֶ֔ם₋4054` `לְמִקְנֵיהֶ֖ם₋4735` `וּלְקִנְיָנָֽם׃₋7075"
    },
    {
        "vid": "6:14:5",
        "tokens": "כַּאֲשֶׁ֨ר₋834` `צִוָּ֤ה₋6680` `יְהוָה֙₋3068` `אֶת־₋853` `מֹשֶׁ֔ה₋4872` `כֵּ֥ן₋3651` `עָשׂ֖וּ₋6213` `בְּנֵ֣י₋1121` `יִשְׂרָאֵ֑ל₋3478` `וַֽיַּחְלְק֖וּ₋2505` `אֶת־₋853` `הָאָֽרֶץ׃₋776` פ"
    },
    {
        "vid": "6:14:6",
        "tokens": "וַיִּגְּשׁ֨וּ₋5066` `בְנֵֽי־₋1121` `יְהוּדָ֤ה₋3063` `אֶל־₋413` `יְהוֹשֻׁ֙עַ֙₋3091` `בַּגִּלְגָּ֔ל₋1537` `וַיֹּ֣אמֶר₋559` `אֵלָ֔יו₋413` `כָּלֵ֥ב₋3612` `בֶּן־₋1121` `יְפֻנֶּ֖ה₋3312` `הַקְּנִזִּ֑י₋7074` `אַתָּ֣ה₋859` `יָדַ֡עְתָּ₋3045` `אֶֽת־₋853` `הַדָּבָר֩₋1697` `אֲשֶׁר־₋834` `דִּבֶּ֨ר₋1696` `יְהוָ֜ה₋3069` `אֶל־₋413` `מֹשֶׁ֣ה₋4872` `אִישׁ־₋376` `הָאֱלֹהִ֗ים₋430` `עַ֧ל₋5921` `אֹדוֹתַ֛י₋182` `וְעַ֥ל₋5921` `אֹדוֹתֶ֖יךָ₋182` בְּקָדֵ֥שׁ `בַּרְנֵֽעַ׃₋6947"
    },
    {
        "vid": "6:14:7",
        "tokens": "בֶּן־₋1121` `אַרְבָּעִ֨ים₋705` `שָׁנָ֜ה₋8141` `אָנֹכִ֗י₋595` `בִּ֠שְׁלֹחַ₋7971` `מֹשֶׁ֨ה₋4872` `עֶֽבֶד־₋5650` `יְהוָ֥ה₋3068` `אֹתִ֛י₋853` מִקָּדֵ֥שׁ `בַּרְנֵ֖עַ₋6947` `לְרַגֵּ֣ל₋7270` `אֶת־₋853` `הָאָ֑רֶץ₋776` `וָאָשֵׁ֤ב₋7725` `אֹתוֹ֙₋853` `דָּבָ֔ר₋1697` `כַּאֲשֶׁ֖ר₋834` `עִם־₋5973` `לְבָבִֽי׃₋3824"
    },
    {
        "vid": "6:14:8",
        "tokens": "וְאַחַי֙₋251` `אֲשֶׁ֣ר₋834` `עָל֣וּ₋5927` `עִמִּ֔י₋5973` `הִמְסִ֖יו₋4529` `אֶת־₋853` `לֵ֣ב₋3820` `הָעָ֑ם₋5971` `וְאָנֹכִ֣י₋595` `מִלֵּ֔אתִי₋4390` `אַחֲרֵ֖י₋310` `יְהוָ֥ה₋3068` `אֱלֹהָֽי׃₋430"
    },
    {
        "vid": "6:14:9",
        "tokens": "וַיִּשָּׁבַ֣ע₋7650` `מֹשֶׁ֗ה₋4872` `בַּיּ֣וֹם₋3117` `הַהוּא֮₋1931` `לֵאמֹר֒₋559` `אִם־₋518` `לֹ֗א₋3808` `הָאָ֙רֶץ֙₋776` `אֲשֶׁ֨ר₋834` `דָּרְכָ֤ה₋1869` `רַגְלְךָ֙₋7272` בָּ֔הּ לְךָ֨ `תִֽהְיֶ֧ה₋1961` `לְנַחֲלָ֛ה₋5159` `וּלְבָנֶ֖יךָ₋1121` `עַד־₋5704` `עוֹלָ֑ם₋5769` `כִּ֣י₋3588` `מִלֵּ֔אתָ₋4390` `אַחֲרֵ֖י₋310` `יְהוָ֥ה₋3068` `אֱלֹהָֽי׃₋430"
    },
    {
        "vid": "6:14:10",
        "tokens": "וְעַתָּ֗ה₋6258` `הִנֵּה֩₋2009` `הֶחֱיָ֨ה₋2421` `יְהוָ֣ה₋3068` ׀ `אוֹתִי֮₋853` `כַּאֲשֶׁ֣ר₋834` `דִּבֵּר֒₋1696` `זֶה֩₋2088` `אַרְבָּעִ֨ים₋705` `וְחָמֵ֜שׁ₋2568` `שָׁנָ֗ה₋8141` `מֵ֠אָז₋227` `דִּבֶּ֨ר₋1696` `יְהוָ֜ה₋3068` `אֶת־₋853` `הַדָּבָ֤ר₋1697` `הַזֶּה֙₋2088` `אֶל־₋413` `מֹשֶׁ֔ה₋4872` `אֲשֶׁר־₋834` `הָלַ֥ךְ₋1980` `יִשְׂרָאֵ֖ל₋3478` `בַּמִּדְבָּ֑ר₋4057` `וְעַתָּה֙₋6258` `הִנֵּ֣ה₋2009` `אָנֹכִ֣י₋595` `הַיּ֔וֹם₋3117` `בֶּן־₋1121` `חָמֵ֥שׁ₋2568` `וּשְׁמוֹנִ֖ים₋8084` `שָׁנָֽה׃₋8141"
    },
    {
        "vid": "6:14:11",
        "tokens": "עוֹדֶ֨נִּי₋5750` `הַיּ֜וֹם₋3117` `חָזָ֗ק₋2389` `כַּֽאֲשֶׁר֙₋834` `בְּי֨וֹם₋3117` `שְׁלֹ֤חַ₋7971` `אוֹתִי֙₋853` `מֹשֶׁ֔ה₋4872` `כְּכֹ֥חִי₋3581` `אָ֖ז₋227` `וּכְכֹ֣חִי₋3581` `עָ֑תָּה₋6258` `לַמִּלְחָמָ֖ה₋4421` `וְלָצֵ֥את₋3318` `וְלָבֽוֹא׃₋935"
    },
    {
        "vid": "6:14:12",
        "tokens": "וְעַתָּ֗ה₋6258` `תְּנָה־₋5414` לִּי֙ `אֶת־₋853` `הָהָ֣ר₋2022` `הַזֶּ֔ה₋2088` `אֲשֶׁר־₋834` `דִּבֶּ֥ר₋1696` `יְהוָ֖ה₋3068` `בַּיּ֣וֹם₋3117` `הַה֑וּא₋1931` `כִּ֣י₋3588` `אַתָּֽה־₋859` `שָׁמַעְתָּ֩₋8085` `בַיּ֨וֹם₋3117` `הַה֜וּא₋1931` `כִּֽי־₋3588` `עֲנָקִ֣ים₋6062` `שָׁ֗ם₋8033` `וְעָרִים֙₋5892` `גְּדֹל֣וֹת₋1419` `בְּצֻר֔וֹת₋1219` `אוּלַ֨י₋194` `יְהוָ֤ה₋3068` `אוֹתִי֙₋854` `וְה֣וֹרַשְׁתִּ֔ים₋3423` `כַּאֲשֶׁ֖ר₋834` `דִּבֶּ֥ר₋1696` `יְהוָֽה׃₋3068"
    },
    {
        "vid": "6:14:13",
        "tokens": "וַֽיְבָרְכֵ֖הוּ₋1288` `יְהוֹשֻׁ֑עַ₋3091` `וַיִּתֵּ֧ן₋5414` `אֶת־₋853` `חֶבְר֛וֹן₋2275` `לְכָלֵ֥ב₋3612` `בֶּן־₋1121` `יְפֻנֶּ֖ה₋3312` `לְנַחֲלָֽה׃₋5159"
    },
    {
        "vid": "6:14:14",
        "tokens": "עַל־₋5921` `כֵּ֣ן₋3651` `הָיְתָֽה־₋1961` `חֶ֠בְרוֹן₋2275` `לְכָלֵ֨ב₋3612` `בֶּן־₋1121` `יְפֻנֶּ֤ה₋3312` `הַקְּנִזִּי֙₋7074` `לְֽנַחֲלָ֔ה₋5159` `עַ֖ד₋5704` `הַיּ֣וֹם₋3117` `הַזֶּ֑ה₋2088` `יַ֚עַן₋3282` `אֲשֶׁ֣ר₋834` `מִלֵּ֔א₋4390` `אַחֲרֵ֕י₋310` `יְהוָ֖ה₋3068` `אֱלֹהֵ֥י₋430` `יִשְׂרָאֵֽל׃₋3478"
    },
    {
        "vid": "6:14:15",
        "tokens": "וְשֵׁ֨ם₋8034` `חֶבְר֤וֹן₋2275` `לְפָנִים֙₋6440` קִרְיַ֣ת `אַרְבַּ֔ע₋7153` `הָאָדָ֧ם₋120` `הַגָּד֛וֹל₋1419` `בָּעֲנָקִ֖ים₋6062` `ה֑וּא₋1931` `וְהָאָ֥רֶץ₋776` `שָׁקְטָ֖ה₋8252` `מִמִּלְחָמָֽה׃₋4421` פ"
    }
]