[
    {
        "vid": "5:33:1",
        "tokens": "וְזֹ֣את₋2063` `הַבְּרָכָ֗ה₋1293` `אֲשֶׁ֨ר₋834` `בֵּרַ֥ךְ₋1288` `מֹשֶׁ֛ה₋4872` `אִ֥ישׁ₋376` `הָאֱלֹהִ֖ים₋430` `אֶת־₋853` `בְּנֵ֣י₋1121` `יִשְׂרָאֵ֑ל₋3478` `לִפְנֵ֖י₋6440` `מוֹתֽוֹ׃₋4194"
    },
    {
        "vid": "5:33:2",
        "tokens": "וַיֹּאמַ֗ר₋559` `יְהוָ֞ה₋3068` `מִסִּינַ֥י₋5514` `בָּא֙₋935` `וְזָרַ֤ח₋2224` `מִשֵּׂעִיר֙₋8165` לָ֔מוֹ `הוֹפִ֙יעַ֙₋3313` `מֵהַ֣ר₋2022` `פָּארָ֔ן₋6290` `וְאָתָ֖ה₋857` `מֵרִבְבֹ֣ת₋7233` `קֹ֑דֶשׁ₋6944` `מִֽימִינ֕וֹ₋3225` [אֵשְׁדָּת כ] (אֵ֥שׁ ק) `(דָּ֖ת₋799` ק) לָֽמוֹ׃"
    },
    {
        "vid": "5:33:3",
        "tokens": "אַ֚ף₋637` `חֹבֵ֣ב₋2245` `עַמִּ֔ים₋5971` `כָּל־₋3605` `קְדֹשָׁ֖יו₋6918` `בְּיָדֶ֑ךָ₋3027` `וְהֵם֙₋1992` `תֻּכּ֣וּ₋8497` `לְרַגְלֶ֔ךָ₋7272` `יִשָּׂ֖א₋5375` `מִדַּבְּרֹתֶֽיךָ׃₋1703"
    },
    {
        "vid": "5:33:4",
        "tokens": "תּוֹרָ֥ה₋8451` `צִוָּה־₋6680` לָ֖נוּ `מֹשֶׁ֑ה₋4872` `מוֹרָשָׁ֖ה₋4181` `קְהִלַּ֥ת₋6952` `יַעֲקֹֽב׃₋3290"
    },
    {
        "vid": "5:33:5",
        "tokens": "וַיְהִ֥י₋1961` `בִישֻׁר֖וּן₋3484` `מֶ֑לֶךְ₋4428` `בְּהִתְאַסֵּף֙₋622` `רָ֣אשֵׁי₋7218` `עָ֔ם₋5971` `יַ֖חַד₋3162` `שִׁבְטֵ֥י₋7626` `יִשְׂרָאֵֽל׃₋3478"
    },
    {
        "vid": "5:33:6",
        "tokens": "יְחִ֥י₋2421` `רְאוּבֵ֖ן₋7205` `וְאַל־₋408` `יָמֹ֑ת₋4191` `וִיהִ֥י₋1961` `מְתָ֖יו₋4962` `מִסְפָּֽר׃₋4557` ס"
    },
    {
        "vid": "5:33:7",
        "tokens": "וְזֹ֣את₋2063` `לִֽיהוּדָה֮₋3063` `וַיֹּאמַר֒₋559` `שְׁמַ֤ע₋8085` `יְהוָה֙₋3068` `ק֣וֹל₋6963` `יְהוּדָ֔ה₋3063` `וְאֶל־₋413` `עַמּ֖וֹ₋5971` `תְּבִיאֶ֑נּוּ₋935` `יָדָיו֙₋3027` `רָ֣ב₋7227` ל֔וֹ `וְעֵ֥זֶר₋5828` `מִצָּרָ֖יו₋6862` `תִּהְיֶֽה׃₋1961` ס"
    },
    {
        "vid": "5:33:8",
        "tokens": "וּלְלֵוִ֣י₋3878` `אָמַ֔ר₋559` `תֻּמֶּ֥יךָ₋8550` `וְאוּרֶ֖יךָ₋224` `לְאִ֣ישׁ₋376` `חֲסִידֶ֑ךָ₋2623` `אֲשֶׁ֤ר₋834` `נִסִּיתוֹ֙₋5254` `בְּמַסָּ֔ה₋4532` `תְּרִיבֵ֖הוּ₋7378` `עַל־₋5921` `מֵ֥י₋4325` `מְרִיבָֽה׃₋4809"
    },
    {
        "vid": "5:33:9",
        "tokens": "הָאֹמֵ֞ר₋559` `לְאָבִ֤יו₋1` `וּלְאִמּוֹ֙₋517` `לֹ֣א₋3808` `רְאִיתִ֔יו₋7200` `וְאֶת־₋853` `אֶחָיו֙₋251` `לֹ֣א₋3808` `הִכִּ֔יר₋5234` `וְאֶת־₋853` [בָּנֹו כ] `(בָּנָ֖יו₋1121` ק) `לֹ֣א₋3808` `יָדָ֑ע₋3045` `כִּ֤י₋3588` `שָֽׁמְרוּ֙₋8104` `אִמְרָתֶ֔ךָ₋565` `וּבְרִֽיתְךָ֖₋1285` `יִנְצֹֽרוּ׃₋5341"
    },
    {
        "vid": "5:33:10",
        "tokens": "יוֹר֤וּ₋3384` `מִשְׁפָּטֶ֙יךָ֙₋4941` `לְיַעֲקֹ֔ב₋3290` `וְתוֹרָתְךָ֖₋8451` `לְיִשְׂרָאֵ֑ל₋3478` `יָשִׂ֤ימוּ₋7760` `קְטוֹרָה֙₋6988` `בְּאַפֶּ֔ךָ₋639` `וְכָלִ֖יל₋3632` `עַֽל־₋5921` `מִזְבְּחֶֽךָ׃₋4196"
    },
    {
        "vid": "5:33:11",
        "tokens": "בָּרֵ֤ךְ₋1288` `יְהוָה֙₋3069` `חֵיל֔וֹ₋2428` `וּפֹ֥עַל₋6467` `יָדָ֖יו₋3027` `תִּרְצֶ֑ה₋7521` `מְחַ֨ץ₋4272` `מָתְנַ֧יִם₋4975` `קָמָ֛יו₋6965` `וּמְשַׂנְאָ֖יו₋8130` `מִן־₋4480` `יְקוּמֽוּן׃₋6965` ס"
    },
    {
        "vid": "5:33:12",
        "tokens": "לְבִנְיָמִ֣ן₋1144` `אָמַ֔ר₋559` `יְדִ֣יד₋3039` `יְהֹוָ֔ה₋3068` `יִשְׁכֹּ֥ן₋7931` `לָבֶ֖טַח₋983` `עָלָ֑יו₋5921` `חֹפֵ֤ף₋2653` `עָלָיו֙₋5921` `כָּל־₋3605` `הַיּ֔וֹם₋3117` `וּבֵ֥ין₋996` `כְּתֵיפָ֖יו₋3802` `שָׁכֵֽן׃₋7931` ס"
    },
    {
        "vid": "5:33:13",
        "tokens": "וּלְיוֹסֵ֣ף₋3130` `אָמַ֔ר₋559` `מְבֹרֶ֥כֶת₋1288` `יְהֹוָ֖ה₋3068` `אַרְצ֑וֹ₋776` `מִמֶּ֤גֶד₋4022` `שָׁמַ֙יִם֙₋8064` `מִטָּ֔ל₋2919` `וּמִתְּה֖וֹם₋8415` `רֹבֶ֥צֶת₋7257` `תָּֽחַת׃₋8478"
    },
    {
        "vid": "5:33:14",
        "tokens": "וּמִמֶּ֖גֶד₋4022` `תְּבוּאֹ֣ת₋8393` `שָׁ֑מֶשׁ₋8121` `וּמִמֶּ֖גֶד₋4022` `גֶּ֥רֶשׁ₋1645` `יְרָחִֽים׃₋3391"
    },
    {
        "vid": "5:33:15",
        "tokens": "וּמֵרֹ֖אשׁ₋7218` `הַרְרֵי־₋2042` `קֶ֑דֶם₋6924` `וּמִמֶּ֖גֶד₋4022` `גִּבְע֥וֹת₋1389` `עוֹלָֽם׃₋5769"
    },
    {
        "vid": "5:33:16",
        "tokens": "וּמִמֶּ֗גֶד₋4022` `אֶ֚רֶץ₋776` `וּמְלֹאָ֔הּ₋4393` `וּרְצ֥וֹן₋7522` `שֹׁכְנִ֖י₋7931` `סְנֶ֑ה₋5572` `תָּב֙וֹאתָה֙₋935` `לְרֹ֣אשׁ₋7218` `יוֹסֵ֔ף₋3130` `וּלְקָדְקֹ֖ד₋6936` `נְזִ֥יר₋5139` `אֶחָֽיו׃₋251"
    },
    {
        "vid": "5:33:17",
        "tokens": "בְּכ֨וֹר₋1060` `שׁוֹר֜וֹ₋7794` `הָדָ֣ר₋1926` ל֗וֹ `וְקַרְנֵ֤י₋7161` `רְאֵם֙₋7214` `קַרְנָ֔יו₋7161` בָּהֶ֗ם `עַמִּ֛ים₋5971` `יְנַגַּ֥ח₋5055` `יַחְדָּ֖ו₋3162` `אַפְסֵי־₋657` `אָ֑רֶץ₋776` `וְהֵם֙₋1992` `רִבְב֣וֹת₋7233` `אֶפְרַ֔יִם₋669` `וְהֵ֖ם₋1992` `אַלְפֵ֥י₋505` `מְנַשֶּֽׁה׃₋4519` ס"
    },
    {
        "vid": "5:33:18",
        "tokens": "וְלִזְבוּלֻ֣ן₋2074` `אָמַ֔ר₋559` `שְׂמַ֥ח₋8055` `זְבוּלֻ֖ן₋2074` `בְּצֵאתֶ֑ךָ₋3318` `וְיִשָּׂשכָ֖ר₋3485` `בְּאֹהָלֶֽיךָ׃₋168"
    },
    {
        "vid": "5:33:19",
        "tokens": "עַמִּים֙₋5971` `הַר־₋2022` `יִקְרָ֔אוּ₋7121` `שָׁ֖ם₋8033` `יִזְבְּח֣וּ₋2076` `זִבְחֵי־₋2077` `צֶ֑דֶק₋6664` `כִּ֣י₋3588` `שֶׁ֤פַע₋8228` `יַמִּים֙₋3220` `יִינָ֔קוּ₋3243` `וּשְׂפוּנֵ֖י₋8226` `טְמ֥וּנֵי₋2934` `חֽוֹל׃₋2344` ס"
    },
    {
        "vid": "5:33:20",
        "tokens": "וּלְגָ֣ד₋1410` `אָמַ֔ר₋559` `בָּר֖וּךְ₋1288` `מַרְחִ֣יב₋7337` `גָּ֑ד₋1410` `כְּלָבִ֣יא₋3833` `שָׁכֵ֔ן₋7931` `וְטָרַ֥ף₋2963` `זְר֖וֹעַ₋2220` `אַף־₋637` `קָדְקֹֽד׃₋6936"
    },
    {
        "vid": "5:33:21",
        "tokens": "וַיַּ֤רְא₋7200` `רֵאשִׁית֙₋7225` ל֔וֹ `כִּי־₋3588` `שָׁ֛ם₋8033` `חֶלְקַ֥ת₋2513` `מְחֹקֵ֖ק₋2710` `סָפ֑וּן₋5603` `וַיֵּתֵא֙₋857` `רָ֣אשֵׁי₋7218` `עָ֔ם₋5971` `צִדְקַ֤ת₋6666` `יְהוָה֙₋3068` `עָשָׂ֔ה₋6213` `וּמִשְׁפָּטָ֖יו₋4941` `עִם־₋5973` `יִשְׂרָאֵֽל׃₋3478` ס"
    },
    {
        "vid": "5:33:22",
        "tokens": "וּלְדָ֣ן₋1835` `אָמַ֔ר₋559` `דָּ֖ן₋1835` `גּ֣וּר₋1482` `אַרְיֵ֑ה₋738` `יְזַנֵּ֖ק₋2187` `מִן־₋4480` `הַבָּשָֽׁן׃₋1316"
    },
    {
        "vid": "5:33:23",
        "tokens": "וּלְנַפְתָּלִ֣י₋5321` `אָמַ֔ר₋559` `נַפְתָּלִי֙₋5321` `שְׂבַ֣ע₋7649` `רָצ֔וֹן₋7522` `וּמָלֵ֖א₋4392` `בִּרְכַּ֣ת₋1293` `יְהוָ֑ה₋3068` `יָ֥ם₋3220` `וְדָר֖וֹם₋1864` `יְרָֽשָׁה׃₋3423` ס"
    },
    {
        "vid": "5:33:24",
        "tokens": "וּלְאָשֵׁ֣ר₋836` `אָמַ֔ר₋559` `בָּר֥וּךְ₋1288` `מִבָּנִ֖ים₋1121` `אָשֵׁ֑ר₋836` `יְהִ֤י₋1961` `רְצוּי֙₋7521` `אֶחָ֔יו₋251` `וְטֹבֵ֥ל₋2881` `בַּשֶּׁ֖מֶן₋8081` `רַגְלֽוֹ׃₋7272"
    },
    {
        "vid": "5:33:25",
        "tokens": "בַּרְזֶ֥ל₋1270` `וּנְחֹ֖שֶׁת₋5178` `מִנְעָלֶ֑יךָ₋4515` `וּכְיָמֶ֖יךָ₋3117` `דָּבְאֶֽךָ׃₋1679"
    },
    {
        "vid": "5:33:26",
        "tokens": "אֵ֥ין₋369` `כָּאֵ֖ל₋410` `יְשֻׁר֑וּן₋3484` `רֹכֵ֤ב₋7392` `שָׁמַ֙יִם֙₋8064` `בְעֶזְרֶ֔ךָ₋5828` `וּבְגַאֲוָת֖וֹ₋1346` `שְׁחָקִֽים׃₋7834"
    },
    {
        "vid": "5:33:27",
        "tokens": "מְעֹנָה֙₋4585` `אֱלֹ֣הֵי₋430` `קֶ֔דֶם₋6924` `וּמִתַּ֖חַת₋8478` `זְרֹעֹ֣ת₋2220` `עוֹלָ֑ם₋5769` `וַיְגָ֧רֶשׁ₋1644` `מִפָּנֶ֛יךָ₋6440` `אוֹיֵ֖ב₋341` `וַיֹּ֥אמֶר₋559` `הַשְׁמֵֽד׃₋8045"
    },
    {
        "vid": "5:33:28",
        "tokens": "וַיִּשְׁכֹּן֩₋7931` `יִשְׂרָאֵ֨ל₋3478` `בֶּ֤טַח₋983` `בָּדָד֙₋910` `עֵ֣ין₋5869` `יַעֲקֹ֔ב₋3290` `אֶל־₋413` `אֶ֖רֶץ₋776` `דָּגָ֣ן₋1715` `וְתִיר֑וֹשׁ₋8492` `אַף־₋637` `שָׁמָ֖יו₋8064` `יַ֥עַרְפוּ₋6201` `טָֽל׃₋2919"
    },
    {
        "vid": "5:33:29",
        "tokens": "אַשְׁרֶ֨יךָ₋835` `יִשְׂרָאֵ֜ל₋3478` `מִ֣י₋4310` `כָמ֗וֹךָ₋3644` `עַ֚ם₋5971` `נוֹשַׁ֣ע₋3467` `בַּֽיהוָ֔ה₋3068` `מָגֵ֣ן₋4043` `עֶזְרֶ֔ךָ₋5828` `וַאֲשֶׁר־₋834` `חֶ֖רֶב₋2719` `גַּאֲוָתֶ֑ךָ₋1346` `וְיִכָּֽחֲשׁ֤וּ₋3584` `אֹיְבֶ֙יךָ֙₋341` לָ֔ךְ `וְאַתָּ֖ה₋859` `עַל־₋5921` `בָּמוֹתֵ֥ימוֹ₋1116` `תִדְרֹֽךְ׃₋1869` ס"
    }
]