[
    {
        "vid": "24:34:1",
        "tokens": "הַדָּבָ֛ר₋1697` `אֲשֶׁר־₋834` `הָיָ֥ה₋1961` `אֶֽל־₋413` `יִרְמְיָ֖הוּ₋3414` `מֵאֵ֣ת₋853` `יְהוָ֑ה₋3068` `וּנְבוּכַדְרֶאצַּ֣ר₋5019` `מֶֽלֶךְ־₋4428` `בָּבֶ֣ל₋894` ׀ `וְכָל־₋3605` `חֵיל֡וֹ₋2428` `וְכָל־₋3605` `מַמְלְכ֣וֹת₋4467` `אֶרֶץ֩₋776` `מֶמְשֶׁ֨לֶת₋4475` `יָד֜וֹ₋3027` `וְכָל־₋3605` `הָעַמִּ֗ים₋5971` `נִלְחָמִ֧ים₋3898` `עַל־₋5921` `יְרוּשָׁלִַ֛ם₋3389` `וְעַל־₋5921` `כָּל־₋3605` `עָרֶ֖יהָ₋5892` `לֵאמֹֽר׃₋559"
    },
    {
        "vid": "24:34:2",
        "tokens": "כֹּֽה־₋3541` `אָמַ֤ר₋559` `יְהוָה֙₋3068` `אֱלֹהֵ֣י₋430` `יִשְׂרָאֵ֔ל₋3478` `הָלֹךְ֙₋1980` `וְאָ֣מַרְתָּ֔₋559` `אֶל־₋413` `צִדְקִיָּ֖הוּ₋6667` `מֶ֣לֶךְ₋4428` `יְהוּדָ֑ה₋3063` `וְאָמַרְתָּ֣₋559` `אֵלָ֗יו₋413` `כֹּ֚ה₋3541` `אָמַ֣ר₋559` `יְהוָ֔ה₋3068` `הִנְנִ֨י₋2005` `נֹתֵ֜ן₋5414` `אֶת־₋853` `הָעִ֤יר₋5892` `הַזֹּאת֙₋2063` `בְּיַ֣ד₋3027` `מֶֽלֶךְ־₋4428` `בָּבֶ֔ל₋894` `וּשְׂרָפָ֖הּ₋8313` `בָּאֵֽשׁ׃₋784"
    },
    {
        "vid": "24:34:3",
        "tokens": "וְאַתָּ֗ה₋859` `לֹ֚א₋3808` `תִמָּלֵט֙₋4422` `מִיָּד֔וֹ₋3027` `כִּ֚י₋3588` `תָּפֹ֣שׂ₋8610` `תִּתָּפֵ֔שׂ₋8610` `וּבְיָד֖וֹ₋3027` `תִּנָּתֵ֑ן₋5414` `וְֽ֠עֵינֶיךָ₋5869` `אֶת־₋853` `עֵינֵ֨י₋5869` `מֶֽלֶךְ־₋4428` `בָּבֶ֜ל₋894` `תִּרְאֶ֗ינָה₋7200` `וּפִ֛יהוּ₋6310` `אֶת־₋854` `פִּ֥יךָ₋6310` `יְדַבֵּ֖ר₋1696` `וּבָבֶ֥ל₋894` `תָּבֽוֹא׃₋935"
    },
    {
        "vid": "24:34:4",
        "tokens": "אַ֚ךְ₋389` `שְׁמַ֣ע₋8085` `דְּבַר־₋1697` `יְהוָ֔ה₋3068` `צִדְקִיָּ֖הוּ₋6667` `מֶ֣לֶךְ₋4428` `יְהוּדָ֑ה₋3063` `כֹּֽה־₋3541` `אָמַ֤ר₋559` `יְהוָה֙₋3068` `עָלֶ֔יךָ₋5921` `לֹ֥א₋3808` `תָמ֖וּת₋4191` `בֶּחָֽרֶב׃₋2719"
    },
    {
        "vid": "24:34:5",
        "tokens": "בְּשָׁל֣וֹם₋7965` `תָּמ֗וּת₋4191` `וּֽכְמִשְׂרְפ֣וֹת₋4955` `אֲ֠בוֹתֶיךָ₋1` `הַמְּלָכִ֨ים₋4428` `הָרִֽאשֹׁנִ֜ים₋7223` `אֲשֶׁר־₋834` `הָי֣וּ₋1961` `לְפָנֶ֗יךָ₋6440` `כֵּ֚ן₋3651` `יִשְׂרְפוּ־₋8313` לָ֔ךְ `וְה֥וֹי₋1945` `אָד֖וֹן₋113` `יִסְפְּדוּ־₋5594` לָ֑ךְ `כִּֽי־₋3588` `דָבָ֥ר₋1697` `אֲנִֽי־₋589` `דִבַּ֖רְתִּי₋1696` `נְאֻם־₋5002` `יְהוָֽה׃₋3068` ס"
    },
    {
        "vid": "24:34:6",
        "tokens": "וַיְדַבֵּר֙₋1696` `יִרְמְיָ֣הוּ₋3414` `הַנָּבִ֔יא₋5030` `אֶל־₋413` `צִדְקִיָּ֖הוּ₋6667` `מֶ֣לֶךְ₋4428` `יְהוּדָ֑ה₋3063` `אֵ֛ת₋853` `כָּל־₋3605` `הַדְּבָרִ֥ים₋1697` `הָאֵ֖לֶּה₋428` `בִּירוּשָׁלִָֽם׃₋3389"
    },
    {
        "vid": "24:34:7",
        "tokens": "וְחֵ֣יל₋2428` `מֶֽלֶךְ־₋4428` `בָּבֶ֗ל₋894` `נִלְחָמִים֙₋3898` `עַל־₋5921` `יְר֣וּשָׁלִַ֔ם₋3389` `וְעַ֛ל₋5921` `כָּל־₋3605` `עָרֵ֥י₋5892` `יְהוּדָ֖ה₋3063` `הַנּֽוֹתָר֑וֹת₋3498` `אֶל־₋413` `לָכִישׁ֙₋3923` `וְאֶל־₋413` `עֲזֵקָ֔ה₋5825` `כִּ֣י₋3588` `הֵ֗נָּה₋2007` `נִשְׁאֲר֛וּ₋7604` `בְּעָרֵ֥י₋5892` `יְהוּדָ֖ה₋3063` `עָרֵ֥י₋5892` `מִבְצָֽר׃₋4013` פ"
    },
    {
        "vid": "24:34:8",
        "tokens": "הַדָּבָ֛ר₋1697` `אֲשֶׁר־₋834` `הָיָ֥ה₋1961` `אֶֽל־₋413` `יִרְמְיָ֖הוּ₋3414` `מֵאֵ֣ת₋853` `יְהוָ֑ה₋3069` `אַחֲרֵ֡י₋310` `כְּרֹת֩₋3772` `הַמֶּ֨לֶךְ₋4428` `צִדְקִיָּ֜הוּ₋6667` `בְּרִ֗ית₋1285` `אֶת־₋854` `כָּל־₋3605` `הָעָם֙₋5971` `אֲשֶׁ֣ר₋834` `בִּירֽוּשָׁלִַ֔ם₋3389` `לִקְרֹ֥א₋7121` `לָהֶ֖ם₋1992` `דְּרֽוֹר׃₋1865"
    },
    {
        "vid": "24:34:9",
        "tokens": "לְ֠שַׁלַּח₋7971` `אִ֣ישׁ₋376` `אֶת־₋853` `עַבְדּ֞וֹ₋5650` `וְאִ֧ישׁ₋376` `אֶת־₋853` `שִׁפְחָת֛וֹ₋8198` `הָעִבְרִ֥י₋5680` `וְהָעִבְרִיָּ֖ה₋5680` `חָפְשִׁ֑ים₋2670` `לְבִלְתִּ֧י₋1115` `עֲבָד־₋5647` בָּ֛ם `בִּיהוּדִ֥י₋3064` `אָחִ֖יהוּ₋251` `אִֽישׁ׃₋376"
    },
    {
        "vid": "24:34:10",
        "tokens": "וַיִּשְׁמְעוּ֩₋8085` `כָל־₋3605` `הַשָּׂרִ֨ים₋8269` `וְכָל־₋3605` `הָעָ֜ם₋5971` `אֲשֶׁר־₋834` `בָּ֣אוּ₋935` `בַבְּרִ֗ית₋1285` `לְ֠שַׁלַּח₋7971` `אִ֣ישׁ₋376` `אֶת־₋853` `עַבְדּ֞וֹ₋5650` `וְאִ֤ישׁ₋376` `אֶת־₋853` `שִׁפְחָתוֹ֙₋8198` `חָפְשִׁ֔ים₋2670` `לְבִלְתִּ֥י₋1115` `עֲבָד־₋5647` בָּ֖ם `ע֑וֹד₋5750` `וַֽיִּשְׁמְע֖וּ₋8085` `וַיְשַׁלֵּֽחוּ׃₋7971"
    },
    {
        "vid": "24:34:11",
        "tokens": "וַיָּשׁ֙וּבוּ֙₋7725` `אַחֲרֵי־₋310` `כֵ֔ן₋3651` `וַיָּשִׁ֗בוּ₋7725` `אֶת־₋853` `הָֽעֲבָדִים֙₋5650` `וְאֶת־₋853` `הַשְּׁפָח֔וֹת₋8198` `אֲשֶׁ֥ר₋834` `שִׁלְּח֖וּ₋7971` `חָפְשִׁ֑ים₋2670` [וַיַּכְבִּישׁוּם כ] `(וַֽיִּכְבְּשׁ֔וּם₋3533` ק) `לַעֲבָדִ֖ים₋5650` `וְלִשְׁפָחֽוֹת׃₋8198` ס"
    },
    {
        "vid": "24:34:12",
        "tokens": "וַיְהִ֤י₋1961` `דְבַר־₋1697` `יְהוָה֙₋3068` `אֶֽל־₋413` `יִרְמְיָ֔הוּ₋3414` `מֵאֵ֥ת₋853` `יְהוָ֖ה₋3068` `לֵאמֹֽר׃₋559"
    },
    {
        "vid": "24:34:13",
        "tokens": "כֹּֽה־₋3541` `אָמַ֥ר₋559` `יְהוָ֖ה₋3068` `אֱלֹהֵ֣י₋430` `יִשְׂרָאֵ֑ל₋3478` `אָנֹכִ֗י₋595` `כָּרַ֤תִּֽי₋3772` `בְרִית֙₋1285` `אֶת־₋854` `אֲב֣וֹתֵיכֶ֔ם₋1` `בְּי֨וֹם₋3117` `הוֹצִאִ֤י₋3318` `אוֹתָם֙₋853` `מֵאֶ֣רֶץ₋776` `מִצְרַ֔יִם₋4714` `מִבֵּ֥ית₋1004` `עֲבָדִ֖ים₋5650` `לֵאמֹֽר׃₋559"
    },
    {
        "vid": "24:34:14",
        "tokens": "מִקֵּ֣ץ₋7093` `שֶׁ֣בַע₋7651` `שָׁנִ֡ים₋8141` `תְּֽשַׁלְּח֡וּ₋7971` `אִישׁ֩₋376` `אֶת־₋853` `אָחִ֨יו₋251` `הָעִבְרִ֜י₋5680` `אֲשֶֽׁר־₋834` `יִמָּכֵ֣ר₋4376` לְךָ֗ `וַעֲבָֽדְךָ֙₋5647` `שֵׁ֣שׁ₋8337` `שָׁנִ֔ים₋8141` `וְשִׁלַּחְתּ֥וֹ₋7971` `חָפְשִׁ֖י₋2670` `מֵֽעִמָּ֑ךְ₋5973` `וְלֹֽא־₋3808` `שָׁמְע֤וּ₋8085` `אֲבֽוֹתֵיכֶם֙₋1` `אֵלַ֔י₋413` `וְלֹ֥א₋3808` `הִטּ֖וּ₋5186` `אֶת־₋853` `אָזְנָֽם׃₋241"
    },
    {
        "vid": "24:34:15",
        "tokens": "וַתָּשֻׁ֨בוּ₋7725` `אַתֶּ֜ם₋859` `הַיּ֗וֹם₋3117` `וַתַּעֲשׂ֤וּ₋6213` `אֶת־₋853` `הַיָּשָׁר֙₋3477` `בְּעֵינַ֔י₋5869` `לִקְרֹ֥א₋7121` `דְר֖וֹר₋1865` `אִ֣ישׁ₋376` `לְרֵעֵ֑הוּ₋7453` `וַתִּכְרְת֤וּ₋3772` `בְרִית֙₋1285` `לְפָנַ֔י₋6440` `בַּבַּ֕יִת₋1004` `אֲשֶׁר־₋834` `נִקְרָ֥א₋7121` `שְׁמִ֖י₋8034` `עָלָֽיו׃₋5921"
    },
    {
        "vid": "24:34:16",
        "tokens": "וַתָּשֻׁ֙בוּ֙₋7725` `וַתְּחַלְּל֣וּ₋2490` `אֶת־₋853` `שְׁמִ֔י₋8034` `וַתָּשִׁ֗בוּ₋7725` `אִ֤ישׁ₋376` `אֶת־₋853` `עַבְדּוֹ֙₋5650` `וְאִ֣ישׁ₋376` `אֶת־₋853` `שִׁפְחָת֔וֹ₋8198` `אֲשֶׁר־₋834` `שִׁלַּחְתֶּ֥ם₋7971` `חָפְשִׁ֖ים₋2670` `לְנַפְשָׁ֑ם₋5315` `וַתִּכְבְּשׁ֣וּ₋3533` `אֹתָ֔ם₋853` `לִֽהְי֣וֹת₋1961` לָכֶ֔ם `לַעֲבָדִ֖ים₋5650` `וְלִשְׁפָחֽוֹת׃₋8198` ס"
    },
    {
        "vid": "24:34:17",
        "tokens": "לָכֵן֮₋3651` `כֹּה־₋3541` `אָמַ֣ר₋559` `יְהוָה֒₋3068` `אַתֶּם֙₋859` `לֹֽא־₋3808` `שְׁמַעְתֶּ֣ם₋8085` `אֵלַ֔י₋413` `לִקְרֹ֣א₋7121` `דְר֔וֹר₋1865` `אִ֥ישׁ₋376` `לְאָחִ֖יו₋251` `וְאִ֣ישׁ₋376` `לְרֵעֵ֑הוּ₋7453` `הִנְנִ֣י₋2005` `קֹרֵא֩₋7121` לָכֶ֨ם `דְּר֜וֹר₋1865` `נְאֻם־₋5002` `יְהוָ֗ה₋3068` `אֶל־₋413` `הַחֶ֙רֶב֙₋2719` `אֶל־₋413` `הַדֶּ֣בֶר₋1698` `וְאֶל־₋413` `הָרָעָ֔ב₋7458` `וְנָתַתִּ֤י₋5414` `אֶתְכֶם֙₋853` [לִזְוָעָה כ] `(לְזַעֲוָ֔ה₋2113` ק) `לְכֹ֖ל₋3605` `מַמְלְכ֥וֹת₋4467` `הָאָֽרֶץ׃₋776"
    },
    {
        "vid": "24:34:18",
        "tokens": "וְנָתַתִּ֣י₋5414` `אֶת־₋853` `הָאֲנָשִׁ֗ים₋376` `הָעֹֽבְרִים֙₋5674` `אֶת־₋853` `בְּרִתִ֔י₋1285` `אֲשֶׁ֤ר₋834` `לֹֽא־₋3808` `הֵקִ֙ימוּ֙₋6965` `אֶת־₋853` `דִּבְרֵ֣י₋1697` `הַבְּרִ֔ית₋1285` `אֲשֶׁ֥ר₋834` `כָּרְת֖וּ₋3772` `לְפָנָ֑י₋6440` `הָעֵ֙גֶל֙₋5695` `אֲשֶׁ֣ר₋834` `כָּרְת֣וּ₋3772` `לִשְׁנַ֔יִם₋8147` `וַיַּעַבְר֖וּ₋5674` `בֵּ֥ין₋996` `בְּתָרָֽיו׃₋1335"
    },
    {
        "vid": "24:34:19",
        "tokens": "שָׂרֵ֨י₋8269` `יְהוּדָ֜ה₋3063` `וְשָׂרֵ֣י₋8269` `יְרוּשָׁלִַ֗ם₋3389` `הַסָּֽרִסִים֙₋5631` `וְהַכֹּ֣הֲנִ֔ים₋3548` `וְכֹ֖ל₋3605` `עַ֣ם₋5971` `הָאָ֑רֶץ₋776` `הָעֹ֣בְרִ֔ים₋5674` `בֵּ֖ין₋996` `בִּתְרֵ֥י₋1335` `הָעֵֽגֶל׃₋5695"
    },
    {
        "vid": "24:34:20",
        "tokens": "וְנָתַתִּ֤י₋5414` `אוֹתָם֙₋853` `בְּיַ֣ד₋3027` `אֹֽיְבֵיהֶ֔ם₋341` `וּבְיַ֖ד₋3027` `מְבַקְשֵׁ֣י₋1245` `נַפְשָׁ֑ם₋5315` `וְהָיְתָ֤ה₋1961` `נִבְלָתָם֙₋5038` `לְמַֽאֲכָ֔ל₋3978` `לְע֥וֹף₋5775` `הַשָּׁמַ֖יִם₋8064` `וּלְבֶהֱמַ֥ת₋929` `הָאָֽרֶץ׃₋776"
    },
    {
        "vid": "24:34:21",
        "tokens": "וְאֶת־₋853` `צִדְקִיָּ֨הוּ₋6667` `מֶֽלֶךְ־₋4428` `יְהוּדָ֜ה₋3063` `וְאֶת־₋853` `שָׂרָ֗יו₋8269` `אֶתֵּן֙₋5414` `בְּיַ֣ד₋3027` `אֹֽיְבֵיהֶ֔ם₋341` `וּבְיַ֖ד₋3027` `מְבַקְשֵׁ֣י₋1245` `נַפְשָׁ֑ם₋5315` `וּבְיַד₋3027` `חֵ֚יל₋2428` `מֶ֣לֶךְ₋4428` `בָּבֶ֔ל₋894` `הָעֹלִ֖ים₋5927` `מֵעֲלֵיכֶֽם׃₋5921"
    },
    {
        "vid": "24:34:22",
        "tokens": "הִנְנִ֨י₋2005` `מְצַוֶּ֜ה₋6680` `נְאֻם־₋5002` `יְהוָ֗ה₋3068` `וַהֲשִׁ֨בֹתִ֜ים₋7725` `אֶל־₋413` `הָעִ֤יר₋5892` `הַזֹּאת֙₋2063` `וְנִלְחֲמ֣וּ₋3898` `עָלֶ֔יהָ₋5921` `וּלְכָד֖וּהָ₋3920` `וּשְׂרָפֻ֣הָ₋8313` `בָאֵ֑שׁ₋784` `וְאֶת־₋853` `עָרֵ֧י₋5892` `יְהוּדָ֛ה₋3063` `אֶתֵּ֥ן₋5414` `שְׁמָמָ֖ה₋8077` `מֵאֵ֥ין₋369` `יֹשֵֽׁב׃₋3427` פ"
    }
]