[
    {
        "vid": "1:23:1",
        "tokens": "Жизни₋2416` `Сарриной₋8283` было `сто₋3967` `₋8141` `двадцать₋6242` `семь₋7651` `лет₋8141`: [вот] `лета₋8141` `₋8141` `жизни₋2416` `Сарриной₋8283`;"
    },
    {
        "vid": "1:23:2",
        "tokens": "и `умерла₋4191` `Сарра₋8283` в `Кириаф-Арбе₋7153`, что [ныне] `Хеврон₋2275`, в `земле₋776` `Ханаанской₋3667`. И `пришел₋935` `Авраам₋85` `рыдать₋5594` по `Сарре₋8283` и `оплакивать₋1058` ее."
    },
    {
        "vid": "1:23:3",
        "tokens": "И `отошел₋6965` `Авраам₋85` от `умершей₋4191` своей, и `говорил₋1696` `сынам₋1121` `Хетовым₋2845`, и `сказал₋559`:"
    },
    {
        "vid": "1:23:4",
        "tokens": "я у вас `пришлец₋1616` и `поселенец₋8453`; `дайте₋5414` мне в `собственность₋272` [место] [для] `гроба₋6913` между вами, чтобы мне `умершую₋4191` мою `схоронить₋6912` от `глаз₋6440` моих."
    },
    {
        "vid": "1:23:5",
        "tokens": "Сыны₋1121` `Хета₋2845` `отвечали₋6030` `Аврааму₋85` и `сказали₋559` ему:"
    },
    {
        "vid": "1:23:6",
        "tokens": "послушай₋8085` нас, `господин₋113` наш; ты `князь₋5387` `Божий₋430` `посреди₋8432` нас; в `лучшем₋4005` из наших `погребальных₋6913` `мест₋6913` `похорони₋6912` `умершую₋4191` твою; `никто₋3808` из нас не `₋376` `откажет₋3607` тебе в `погребальном₋6913` `месте₋6913`, для `погребения₋6912` `умершей₋4191` твоей."
    },
    {
        "vid": "1:23:7",
        "tokens": "Авраам₋85` `встал₋6965` и `поклонился₋7812` `народу₋5971` `земли₋776` той, `сынам₋1121` `Хетовым₋2845`;"
    },
    {
        "vid": "1:23:8",
        "tokens": "и `говорил₋1696` им и `сказал₋559`: если вы `согласны₋3426`, чтобы я `₋5315` `похоронил₋6912` `умершую₋4191` мою, то `послушайте₋8085` меня, `попросите₋6293` за меня `Ефрона₋6085`, `сына₋1121` `Цохарова₋6714`,"
    },
    {
        "vid": "1:23:9",
        "tokens": "чтобы он `отдал₋5414` мне `пещеру₋4631` `Махпелу₋4375`, которая у него на `конце₋7097` `поля₋7704` его, чтобы за `довольную₋4392` `цену₋3701` `отдал₋5414` ее мне `посреди₋8432` вас, в `собственность₋272` для `погребения₋6913`."
    },
    {
        "vid": "1:23:10",
        "tokens": "Ефрон₋6085` же `сидел₋3427` `посреди₋8432` `сынов₋1121` `Хетовых₋2845`; и `отвечал₋6030` `Ефрон₋6085` `Хеттеянин₋2850` `Аврааму₋85` `вслух₋241` `сынов₋1121` `Хета₋2845`, всех `входящих₋935` во `врата₋8179` `города₋5892` его, и `сказал₋559`:"
    },
    {
        "vid": "1:23:11",
        "tokens": "нет₋3808`, `господин₋113` мой, `послушай₋8085` меня: я `даю₋5414` тебе `поле₋7704` и `пещеру₋4631`, которая на нем, `даю₋5414` тебе, пред `очами₋5869` `сынов₋1121` `народа₋5971` моего `дарю₋5414` тебе ее, `похорони₋6912` `умершую₋4191` твою."
    },
    {
        "vid": "1:23:12",
        "tokens": "Авраам₋85` `поклонился₋7812` `пред₋3942` `народом₋5971` `земли₋776` той"
    },
    {
        "vid": "1:23:13",
        "tokens": "и `говорил₋1696` `Ефрону₋6085` `вслух₋241` `народа₋5971` `земли₋776` той и `сказал₋559`: `если₋3863` `послушаешь₋8085`, я `даю₋5414` тебе за `поле₋7704` `серебро₋3701`; `возьми₋3947` у меня, и я `похороню₋6912` там `умершую₋4191` мою."
    },
    {
        "vid": "1:23:14",
        "tokens": "Ефрон₋6085` `отвечал₋6030` `Аврааму₋85` и `сказал₋559` ему:"
    },
    {
        "vid": "1:23:15",
        "tokens": "господин₋113` мой! `послушай₋8085` меня: `земля₋776` [стоит] `четыреста₋702` `₋3967` `сиклей₋8255` `серебра₋3701`; `для₋996` меня и для тебя что это? `похорони₋6912` `умершую₋4191` твою."
    },
    {
        "vid": "1:23:16",
        "tokens": "Авраам₋85` `выслушал₋8085` `Ефрона₋6085`; и `отвесил₋8254` `Авраам₋85` `Ефрону₋6085` `серебра₋3701`, сколько он `объявил₋1696` `вслух₋241` `сынов₋1121` `Хетовых₋2845`, `четыреста₋702` `₋3967` `сиклей₋8255` `серебра₋3701`, какое `ходит₋5674` у `купцов₋5503`."
    },
    {
        "vid": "1:23:17",
        "tokens": "И `стало₋6965` `поле₋7704` `Ефроново₋6085`, которое при `Махпеле₋4375`, `против₋3942` `Мамре₋4471`, `поле₋7704` и `пещера₋4631`, которая на нем, и все `деревья₋6086`, которые на `поле₋7704`, во всех `пределах₋1366` его `вокруг₋5439`,"
    },
    {
        "vid": "1:23:18",
        "tokens": "владением₋4736` `Авраамовым₋85` пред `очами₋5869` `сынов₋1121` `Хета₋2845`, всех `входящих₋935` во `врата₋8179` `города₋5892` его."
    },
    {
        "vid": "1:23:19",
        "tokens": "После₋310` `сего₋3651` `Авраам₋85` `похоронил₋6912` `Сарру₋8283`, `жену₋802` свою, в `пещере₋4631` `поля₋7704` в `Махпеле₋4375`, `против₋5921` `₋6440` `Мамре₋4471`, что [ныне] `Хеврон₋2275`, в `земле₋776` `Ханаанской₋3667`."
    },
    {
        "vid": "1:23:20",
        "tokens": "Так `достались₋6965` `Аврааму₋85` от `сынов₋1121` `Хетовых₋2845` `поле₋7704` и `пещера₋4631`, которая на нем, в `собственность₋272` для `погребения₋6913`."
    }
]